{"test_output":"Building and testing Dist-Zilla-Plugin-Authority-1.009\nBuilding Dist-Zilla-Plugin-Authority\nt/00-compile.t ................ ok\n# \n# \n# Generated by Dist::Zilla::Plugin::ReportVersions::Tiny v1.10\n# perl: 5.029000 (wanted 5.006) on freebsd from /usr/home/jkeenan/var/tad/testing/perl-5.29.0/bin/perl\n# \n# Dist::Zilla::Role::FileFinderUser             => 6.012      (want 4.102345)\n# Dist::Zilla::Role::FileMunger                 => 6.012      (want 4.102345)\n# Dist::Zilla::Role::MetaProvider               => 6.012      (want 4.102345)\n# Dist::Zilla::Role::PPI                        => 6.012      (want 4.300001)\n# Dist::Zilla::Util                             => 6.012      (want any version)\n# File::HomeDir                                 => 1.004      (want any version)\n# File::Spec                                    => 3.74       (want any version)\n# File::Temp                                    => 0.2304     (want any version)\n# IO::Handle                                    => 1.39       (want any version)\n# IPC::Open3                                    => 1.20       (want any version)\n# Module::Build                                 => 0.4224     (want 0.28)   \n# Moose                                         => 2.2011     (want 1.03)   \n# Moose::Util::TypeConstraints                  => 2.2011     (want 1.01)   \n# PPI                                           => 1.236      (want 1.206)  \n# Test::More                                    => 1.302136   (want 0.88)   \n# strict                                        => 1.11       (want any version)\n# warnings                                      => 1.42       (want any version)\n# \n# Thanks for using my code.  I hope it works for you.\n# If not, please try and include this output in the bug report.\n# That will help me reproduce the issue and solve your problem.\n# \nt/000-report-versions-tiny.t .. ok\nt/apocalypse.t ................ skipped: Test::Apocalypse required for validating the distribution\nAll tests successful.\nFiles=3, Tests=2,  1 wallclock secs ( 0.02 usr  0.01 sys +  0.60 cusr  0.29 csys =  0.91 CPU)\nResult: PASS\n","author":"APOCAL","grade":"PASS","distversion":"1.009","via":"App::cpanminus::reporter 0.17 (1.7043)","dist":"Dist-Zilla-Plugin-Authority","prereqs":null,"distname":"Dist-Zilla-Plugin-Authority-1.009"}
